zkbapp1/__init__.py
zkbapp1/greet1.py
zkbapp2/__init__.py
zkbapp2/greet2.py
zkbfirstApp-8.0.2.dist-info/METADATA
zkbfirstApp-8.0.2.dist-info/WHEEL
zkbfirstApp-8.0.2.dist-info/top_level.txt
zkbfirstApp-8.0.2.dist-info/RECORD
